digitalai/__init__.py
digitalai/release/__init__.py
digitalai/release/release_api_client.py
digitalai/release/integration/__init__.py
digitalai/release/integration/base_task.py
digitalai/release/integration/exceptions.py
digitalai/release/integration/input_context.py
digitalai/release/integration/job_data_encryptor.py
digitalai/release/integration/k8s.py
digitalai/release/integration/logger.py
digitalai/release/integration/masked_io.py
digitalai/release/integration/output_context.py
digitalai/release/integration/reporting_records.py
digitalai/release/integration/watcher.py
digitalai/release/integration/wrapper.py
digitalai_release_sdk-25.3.1.dist-info/METADATA
digitalai_release_sdk-25.3.1.dist-info/WHEEL
digitalai_release_sdk-25.3.1.dist-info/licenses/LICENSE
digitalai_release_sdk-25.3.1.dist-info/RECORD
