Metadata-Version: 2.4
Name: digitalai_release_sdk
Version: 25.3.1
Summary: Digital.ai Release SDK
Project-URL: Homepage, https://digital.ai/
Project-URL: Documentation, https://docs.digital.ai/release/docs/category/python-sdk
Author-email: "Digital.ai" <pypi-devops@digital.ai>
License-File: LICENSE
Classifier: Development Status :: 5 - Production/Stable
Classifier: Intended Audience :: Developers
Classifier: License :: OSI Approved :: MIT License
Classifier: Operating System :: OS Independent
Classifier: Programming Language :: Python :: 3
Classifier: Programming Language :: Python :: 3.8
Classifier: Programming Language :: Python :: 3.9
Classifier: Programming Language :: Python :: 3.10
Classifier: Programming Language :: Python :: 3.11
Classifier: Programming Language :: Python :: 3.12
Classifier: Topic :: Software Development :: Libraries
Requires-Python: >=3.8
Requires-Dist: dataclasses-json>=0.6.7
Requires-Dist: kubernetes>=32.0.1
Requires-Dist: pycryptodomex>=3.21.0
Requires-Dist: python-dateutil>=2.9.0
Requires-Dist: requests>=2.32.3
